assemblyline_v4_p2compat/__init__.py
assemblyline_v4_p2compat/common/__init__.py
assemblyline_v4_p2compat/common/dict_utils.py
assemblyline_v4_p2compat/common/forge.py
assemblyline_v4_p2compat/common/isotime.py
assemblyline_v4_p2compat/common/log.py
assemblyline_v4_p2compat/common/logformat.py
assemblyline_v4_p2compat/common/net.py
assemblyline_v4_p2compat/common/str_utils.py
assemblyline_v4_p2compat-4.0.0.dev7.dist-info/LICENCE.md
assemblyline_v4_p2compat-4.0.0.dev7.dist-info/METADATA
assemblyline_v4_p2compat-4.0.0.dev7.dist-info/WHEEL
assemblyline_v4_p2compat-4.0.0.dev7.dist-info/top_level.txt
assemblyline_v4_p2compat-4.0.0.dev7.dist-info/RECORD
