Metadata-Version: 2.1
Name: assemblyline-v4-p2compat
Version: 4.0.0.dev7
Summary: Assemblyline 4 python2 service compatibility layer
Home-page: https://bitbucket.org/cse-assemblyline/assemblyline_v4_p2compat/
Author: CCCS Assemblyline development team
Author-email: assemblyline@cyber.gc.ca
License: MIT
Keywords: assemblyline malware gc canada cse-cst cse cst cyber cccs
Platform: UNKNOWN
Classifier: Development Status :: 2 - Pre-Alpha
Classifier: Intended Audience :: Developers
Classifier: Topic :: Software Development :: Libraries
Classifier: License :: OSI Approved :: MIT License
Classifier: Programming Language :: Python :: 2.7
Requires-Dist: PyYAML
Requires-Dist: netifaces
Requires-Dist: easydict
Requires-Dist: chardet
